[
	{
		"id": 61,
		"description": "Service excellent, fortement recommandé.",
		"Image": "REF001picture",
		"Stock": 30,
		"Prix": 8.90,
		"Référence": "REF001",
		"Catégorie": 1,
		"Fournisseur": 1,
		"Titre": "L'inconnue de la Seine",
		"Auteur": "Guillaume Musso",
		"Note": 5.0000
	},
	{
		"id": 62,
		"description": "Bonne expérience globale. Pourrait s'améliorer dans certains domaines.",
		"Image": "REF002picture",
		"Stock": 21,
		"Prix": 8.90,
		"Référence": "REF002",
		"Catégorie": 1,
		"Fournisseur": 1,
		"Titre": "Skidamarink",
		"Auteur": "Guillaume Musso",
		"Note": 4.0000
	},
	{
		"id": 63,
		"description": "Service moyen. Place à l'amélioration.",
		"Image": "REF003picture",
		"Stock": 5,
		"Prix": 12.90,
		"Référence": "REF003",
		"Catégorie": 1,
		"Fournisseur": 1,
		"Titre": "Marche ou Crève",
		"Auteur": "Stephen King",
		"Note": 3.0000
	},
	{
        "id": 64,
        "description": "Fantastique ! Reviendra certainement.",
        "Image": "REF004picture",
        "Stock": 52,
        "Prix": 7.90,
        "Référence": "REF004",
        "Catégorie": 1,
        "Fournisseur": 2,
        "Titre": "Le blé en herbe",
        "Auteur": "Colette",
        "Note": 5.0000
    },
    {
        "id": 65,
        "description": "Pas satisfait du service. Doit s'améliorer.",
        "Image": "REF004picture",
        "Stock": 52,
        "Prix": 7.90,
        "Référence": "REF004",
        "Catégorie": 1,
        "Fournisseur": 2,
        "Titre": "Le blé en herbe",
        "Auteur": "Colette",
        "Note": 2.0000
    },
    {
        "id": 66,
        "description": "Excellent rapport qualité-prix.",
        "Image": "REF005picture",
        "Stock": 2,
        "Prix": 12.90,
        "Référence": "REF005",
        "Catégorie": 1,
        "Fournisseur": 3,
        "Titre": "1991",
        "Auteur": "Franck Thilliez",
        "Note": 4.0000
    },
	{
        "id": 67,
        "description": "Expérience correcte, mais pas exceptionnelle.",
        "Image": "REF002picture",
        "Stock": 21,
        "Prix": 8.90,
        "Référence": "REF002",
        "Catégorie": 1,
        "Fournisseur": 1,
        "Titre": "Skidamarink",
        "Auteur": "Guillaume Musso",
        "Note": 3.0000
    },
    {
        "id": 68,
        "description": "Personnel et installations incroyables.",
        "Image": "REF005picture",
        "Stock": 2,
        "Prix": 12.90,
        "Référence": "REF005",
        "Catégorie": 1,
        "Fournisseur": 3,
        "Titre": "1991",
        "Auteur": "Franck Thilliez",
        "Note": 5.0000
    },
    {
        "id": 69,
        "description": "Très satisfait du service.",
        "Image": "REF030picture",
        "Stock": 28,
        "Prix": 15.90,
        "Référence": "REF030",
        "Catégorie": 3,
        "Fournisseur": 2,
        "Titre": "La bible des huiles essentielles",
        "Auteur": "Danièle Festy",
        "Note": 4.0000
    },
	{
        "id": 70,
        "description": "Expérience décevante. Doit être grandement améliorée.",
        "Image": "REF001picture",
        "Stock": 30,
        "Prix": 8.90,
        "Référence": "REF001",
        "Catégorie": 1,
        "Fournisseur": 1,
        "Titre": "L'inconnue de la Seine",
        "Auteur": "Guillaume Musso",
        "Note": 2.0000
    },
    {
        "id": 71,
        "description": "Personnel amical et environnement propre.",
        "Image": "REF027picture",
        "Stock": 30,
        "Prix": 8.90,
        "Référence": "REF027",
        "Catégorie": 1,
        "Fournisseur": 1,
        "Titre": "La guerre invisible",
        "Auteur": "Leila Minano",
        "Note": 4.0000
    },
    {
        "id": 72,
        "description": "Correct, mais il y a de meilleures options disponibles.",
        "Image": "REF014picture",
        "Stock": 30,
        "Prix": 8.90,
        "Référence": "REF014",
        "Catégorie": 1,
        "Fournisseur": 3,
        "Titre": "127 heures",
        "Auteur": "Aron Ralston",
        "Note": 3.0000
    },
	{
        "id": 73,
        "description": "Service exceptionnel !",
        "Image": "REF002picture",
        "Stock": 21,
        "Prix": 8.90,
        "Référence": "REF002",
        "Catégorie": 1,
        "Fournisseur": 1,
        "Titre": "Skidamarink",
        "Auteur": "Guillaume Musso",
        "Note": 5.0000
    },
    {
        "id": 74,
        "description": "Satisfait de l'expérience globale.",
        "Image": "REF014picture",
        "Stock": 30,
        "Prix": 8.90,
        "Référence": "REF014",
        "Catégorie": 1,
        "Fournisseur": 3,
        "Titre": "127 heures",
        "Auteur": "Aron Ralston",
        "Note": 4.0000
    },
    {
        "id": 75,
        "description": "Service moyen, rien de spécial.",
        "Image": "REF029picture",
        "Stock": 12,
        "Prix": 8.90,
        "Référence": "REF029",
        "Catégorie": 1,
        "Fournisseur": 2,
        "Titre": "L'armée au féminin",
        "Auteur": "Jean Marc Tanguy",
        "Note": 3.0000
    },
	{
        "id": 76,
        "description": "Exceptionnel ! Recommanderais à d'autres.",
        "Image": "REF017picture",
        "Stock": 20,
        "Prix": 8.90,
        "Référence": "REF017",
        "Catégorie": 2,
        "Fournisseur": 2,
        "Titre": "Dragon Ball tome 3",
        "Auteur": "Toriyama Akira",
        "Note": 5.0000
    },
    {
        "id": 77,
        "description": "Bon service, mais un peu cher.",
        "Image": "REF026picture",
        "Stock": 23,
        "Prix": 8.90,
        "Référence": "REF026",
        "Catégorie": 3,
        "Fournisseur": 1,
        "Titre": "Le grand livre des DIY",
        "Auteur": "Emilie Guelpa",
        "Note": 4.0000
    },
    {
        "id": 78,
        "description": "Expérience désagréable. Doit être considérablement améliorée.",
        "Image": "REF013picture",
        "Stock": 8,
        "Prix": 8.90,
        "Référence": "REF013",
        "Catégorie": 1,
        "Fournisseur": 3,
        "Titre": "Brulée vive",
        "Auteur": "Souad",
        "Note": 2.0000
    },
	{
        "id": 79,
        "description": "Content du service fourni.",
        "Image": "REF006picture",
        "Stock": 23,
        "Prix": 8.90,
        "Référence": "REF006",
        "Catégorie": 1,
        "Fournisseur": 1,
        "Titre": "Cujo",
        "Auteur": "Stephen King",
        "Note": 4.0000
    },
    {
        "id": 80,
        "description": "Pourrait être meilleur, mais pas terrible.",
        "Image": "REF022picture",
        "Stock": 8,
        "Prix": 8.90,
        "Référence": "REF022",
        "Catégorie": 1,
        "Fournisseur": 3,
        "Titre": "Harry Potter à l'école des sorciers",
        "Auteur": "J.K. Rowling",
        "Note": 3.0000
    }
]
